Metadata-Version: 2.1
Name: distribution-package
Version: 1.0
Summary: Gaussian and Binomial distributions
Home-page: UNKNOWN
Author: Dung Hoang
Author-email: dung.hoang300699@gmail.com
License: UNKNOWN
Platform: UNKNOWN
